pylibsythe/__init__.py
pylibsythe/pylibsythe.pyd
pylibsythe/pylibsythe.pyi
pylibsythe-0.0.1.dist-info/METADATA
pylibsythe-0.0.1.dist-info/WHEEL
pylibsythe-0.0.1.dist-info/top_level.txt
pylibsythe-0.0.1.dist-info/RECORD
