Metadata-Version: 2.1
Name: pylibsythe
Version: 0.0.1
Summary: pylibsythe
Home-page: https://gitlab.com/tandemdude/pylibsythe
Author: tandemdude
Author-email: tandemdude1@gmail.com
License: UNKNOWN
Platform: UNKNOWN
Classifier: Development Status :: 3 - Alpha
Classifier: Intended Audience :: Developers
Classifier: Natural Language :: English
Classifier: Topic :: Software Development :: Libraries :: Python Modules
Classifier: Programming Language :: Python :: 3.8
Classifier: Programming Language :: Python :: 3 :: Only
Requires-Python: >=3.8.3
